main.py
yhddnotification-1.0.1.dist-info/METADATA
yhddnotification-1.0.1.dist-info/WHEEL
yhddnotification-1.0.1.dist-info/top_level.txt
yhddnotification-1.0.1.dist-info/RECORD
