Metadata-Version: 2.1
Name: yhddnotification
Version: 1.0.1
Summary: test mode
Home-page: UNKNOWN
Author: BrYan
Author-email: mail0426@163.com
License: UNKNOWN
Platform: UNKNOWN
